{
  "project_info": {
    "project_number": "343672419152",
    "firebase_url": "https://masaarajman.firebaseio.com",
    "project_id": "masaarajman",
    "storage_bucket": "masaarajman.appspot.com"
  },
  "client": [
    {
      "client_info": {
        "mobilesdk_app_id": "1:343672419152:android:215c05a78348a45e",
        "android_client_info": {
          "package_name": "com.incube.ajmanptc"
        }
      },
      "oauth_client": [
        {
          "client_id": "343672419152-e3jqd9355pkohi92sp32n80bgtk545o2.apps.googleusercontent.com",
          "client_type": 3
        }
      ],
      "api_key": [
        {
          "current_key": "AIzaSyAVqF0ROD0vqM6SIfUr5HtH60OC6ivXT9c"
        }
      ],
      "services": {
        "analytics_service": {
          "status": 1
        },
        "appinvite_service": {
          "status": 1,
          "other_platform_oauth_client": []
        },
        "ads_service": {
          "status": 2
        }
      }
    }
  ],
  "configuration_version": "1"
}